tests/__init__.py
tests/test_fundamentals.py
valinvest/__init__.py
valinvest/__version__.py
valinvest/config.py
valinvest/fundamentals.py
valinvest/main.py
valinvest-0.0.2.dist-info/LICENSE
valinvest-0.0.2.dist-info/METADATA
valinvest-0.0.2.dist-info/WHEEL
valinvest-0.0.2.dist-info/top_level.txt
valinvest-0.0.2.dist-info/RECORD
