Metadata-Version: 2.1
Name: valinvest
Version: 0.0.2
Summary: A value investing tool based on Warren Buffett, Joseph Piotroski and Benjamin Graham thoughts
Home-page: https://github.com/astro30/valinvest
Author: Guillaume Rey
License: UNKNOWN
Platform: UNKNOWN
Classifier: Programming Language :: Python :: 3
Classifier: License :: OSI Approved :: MIT License
Classifier: Operating System :: OS Independent
Requires-Python: >=3.6
